data/gm.mrc.mdoc
data/nav.nav
LICENCE
pyserialem/__init__.py
pyserialem/montage.py
pyserialem/navigation.py
pyserialem/reader.py
pyserialem/utils.py
setup.py
tests/conftest.py
tests/test_bin_ndarray.py
tests/test_io.py
tests/test_items.py
pyserialem-0.3.2.dist-info/WHEEL
pyserialem-0.3.2.dist-info/METADATA
pyserialem-0.3.2.dist-info/RECORD
