Metadata-Version: 2.1
Name: pyserialem
Version: 0.3.2
Summary: Python module to read/write SerialEM .nav files.
Home-page: http://github.com/stefsmeets/pyserialem
License: BSD-3-Clause
Keywords: serialem,electron-microscopy,navigator
Author: Stef Smeets
Author-email: s.smeets@tudelft.nl
Maintainer: Stef Smeets
Maintainer-email: s.smeets@tudelft.nl
Requires-Python: >=3.6.1
Classifier: Development Status :: 4 - Beta
Classifier: Intended Audience :: Developers
Classifier: License :: OSI Approved :: BSD License
Classifier: Programming Language :: Python :: 3
Classifier: Programming Language :: Python :: 3.6
Classifier: Programming Language :: Python :: 3.7
Classifier: Programming Language :: Python :: 3.8
Classifier: Programming Language :: Python :: 3.9
Classifier: Topic :: Software Development :: Libraries
Requires-Dist: lmfit (>=1.0.1)
Requires-Dist: matplotlib (>=3.1.2)
Requires-Dist: mrcfile (>=1.1.2)
Requires-Dist: numpy (>=1.17.3)
Requires-Dist: scikit-image (>=0.17.2)
Requires-Dist: scipy (>=1.5.0)
Requires-Dist: tqdm (>=4.46.1)
Project-URL: Bug Reports, https://github.com/stefsmeets/pyserialem/issues
Project-URL: Documentation, http://github.com/stefsmeets/pyserialem
Project-URL: Repository, http://github.com/stefsmeets/pyserialem
